canvas_utilities/__init__.py
canvas_utilities/compare_image_hash.py
canvas_utilities/image_channel_utils.py
canvas_utilities/image_color_adjust.py
canvas_utilities/image_shadow.py
canvas_utilities/image_transform.py
canvas_utilities/image_utils.py
canvas_utilities/image_utils_2.py
canvas_utilities/map_editor.py
canvas_utilities/psd_compositer.py
canvas_utilities/skimage_utils.py
canvas_utilities/sprite_utils.py
canvas_utilities/utils/__init__.py
canvas_utilities/utils/decorator.py
canvas_utilities/utils/io_helper.py
canvas_utilities/utils/logging.py
canvas_utilities/utils/mime_types.py
canvas_utilities-0.1.3.dist-info/LICENSE
canvas_utilities-0.1.3.dist-info/METADATA
canvas_utilities-0.1.3.dist-info/WHEEL
canvas_utilities-0.1.3.dist-info/top_level.txt
canvas_utilities-0.1.3.dist-info/RECORD
